superpandas/__init__.py
superpandas/config.py
superpandas/langgraph_agent.py
superpandas/llm_client.py
superpandas/pandasql.py
superpandas/providers.py
superpandas/superdataframe.py
superpandas/templates.py
superpandas/utils/__init__.py
superpandas/utils/codeparser.py
superpandas/utils/executors.py
superpandas-0.4.0.dist-info/METADATA
superpandas-0.4.0.dist-info/WHEEL
superpandas-0.4.0.dist-info/licenses/LICENSE
superpandas-0.4.0.dist-info/RECORD
