Metadata-Version: 2.4
Name: superpandas
Version: 0.4.0
Summary: Lightweight wrapper around Pandas to add AI capabilities
Author-email: Haris Jabbar <haris@superpandas.ai>
License: MIT
License-File: LICENSE
Requires-Python: >=3.8
Requires-Dist: langchain-core>=0.2.0
Requires-Dist: langgraph>=0.2.0
Requires-Dist: numpy>=1.20.0
Requires-Dist: pandas>=1.0.0
Requires-Dist: smolagents>=0.1.0
Provides-Extra: test
Requires-Dist: pytest-cov>=4.0.0; extra == 'test'
Requires-Dist: pytest>=7.0.0; extra == 'test'
